{"trial_id": "5129aed0b6bcc0bbd757eae4af7ca249", "hyperparameters": {"space": [{"class_name": "Int", "config": {"name": "numlayers", "default": null, "conditions": [], "min_value": 1, "max_value": 4, "step": 1, "sampling": null}}, {"class_name": "Int", "config": {"name": "units0", "default": null, "conditions": [], "min_value": 16, "max_value": 256, "step": 16, "sampling": null}}, {"class_name": "Choice", "config": {"name": "activation", "default": "relu", "conditions": [], "values": ["relu", "leaky_relu", "elu", "tanh"], "ordered": false}}, {"class_name": "Boolean", "config": {"name": "dropout", "default": false, "conditions": []}}, {"class_name": "Boolean", "config": {"name": "bn_after_act", "default": false, "conditions": []}}, {"class_name": "Int", "config": {"name": "units1", "default": null, "conditions": [], "min_value": 16, "max_value": 256, "step": 16, "sampling": null}}, {"class_name": "Int", "config": {"name": "units2", "default": null, "conditions": [], "min_value": 16, "max_value": 256, "step": 16, "sampling": null}}, {"class_name": "Int", "config": {"name": "units3", "default": null, "conditions": [], "min_value": 16, "max_value": 256, "step": 16, "sampling": null}}], "values": {"numlayers": 2, "units0": 144, "activation": "elu", "dropout": true, "bn_after_act": false, "units1": 80, "units2": 32, "units3": 80}}, "metrics": {"metrics": {"loss": {"direction": "min", "observations": [{"value": [0.37881723046302795], "step": 0}]}, "root_mean_squared_error": {"direction": "min", "observations": [{"value": [0.6154812574386597], "step": 0}]}, "mean_absolute_percentage_error": {"direction": "min", "observations": [{"value": [9.332255363464355], "step": 0}]}, "val_loss": {"direction": "min", "observations": [{"value": [0.015364290680736303], "step": 0}]}, "val_root_mean_squared_error": {"direction": "min", "observations": [{"value": [0.12392695248126984], "step": 0}]}, "val_mean_absolute_percentage_error": {"direction": "min", "observations": [{"value": [1.8334793448448181], "step": 0}]}}}, "score": 0.015364290680736303, "best_step": 0, "status": "COMPLETED"}